PyTyle/Config.py
PyTyle/Debug.py
PyTyle/Desktop.py
PyTyle/Event.py
PyTyle/Probe.py
PyTyle/Screen.py
PyTyle/State.py
PyTyle/Tile.py
PyTyle/TileState.py
PyTyle/TileStorage.py
PyTyle/Viewport.py
PyTyle/Window.py
PyTyle/__init__.py
PyTyle/Tilers/Cascade.py
PyTyle/Tilers/Horizontal.py
PyTyle/Tilers/HorizontalRows.py
PyTyle/Tilers/Maximal.py
PyTyle/Tilers/TileDefault.py
PyTyle/Tilers/Vertical.py
PyTyle/Tilers/__init__.py
pytyle1x-1.3.999.data/scripts/pytyle1x
pytyle1x-1.3.999.dist-info/LICENSE
pytyle1x-1.3.999.dist-info/METADATA
pytyle1x-1.3.999.dist-info/WHEEL
pytyle1x-1.3.999.dist-info/top_level.txt
pytyle1x-1.3.999.dist-info/RECORD
