Metadata-Version: 2.1
Name: pytyle1x
Version: 1.3.999
Summary: A tiling manager for EWMH compliant window managers
Home-page: https://gitlab.com/zehkira/pytyle1x
Author: zehkira
License: UNKNOWN
Platform: UNKNOWN
Classifier: Programming Language :: Python :: 3.6
Classifier: License :: OSI Approved :: GNU General Public License v3 (GPLv3)
Classifier: Operating System :: POSIX :: Linux
Classifier: Topic :: Desktop Environment :: Window Managers
Requires-Python: >=3.6
License-File: LICENSE
Requires-Dist: python-xlib
